ai_claim_essence/__init__.py
ai_claim_essence/main.py
ai_claim_essence/prompts.py
ai_claim_essence-2025.12.20202921.dist-info/METADATA
ai_claim_essence-2025.12.20202921.dist-info/WHEEL
ai_claim_essence-2025.12.20202921.dist-info/top_level.txt
ai_claim_essence-2025.12.20202921.dist-info/RECORD
