Metadata-Version: 2.4
Name: ai-claim-essence
Version: 2025.12.20202921
Summary: A new package that lets users input a short statement about AI’s societal impact and instantly receives a clear, structured summary of the core idea. By focusing on extracting the essence of the claim
Author-email: ai-claim-essence <hi@eugene.plus>
License: MIT
Project-URL: Homepage, https://github.com/chigwell/ai-claim-essence
Requires-Python: >=3.9
Requires-Dist: langchain-llm7>=0.0.0
Requires-Dist: llmatch-messages>=0.0.0
Requires-Dist: langchain-core>=0.3.0
